CHANGES.rst
LICENSE
MANIFEST.in
README.rst
setup.cfg
setup.py
tox.ini
docs/CHANGES.rst
docs/CoreExposed.jython.rst
docs/README.rst
docs/conf.py
docs/index.rst
docs/_static/.keep
docs/_templates/.keep
src/jt/__init__.py
src/jt/jython.cfg
src/jt/jython/__about__.py
src/jt/jython/__config__.py
src/jt/jython/__init__.py
src/jtypes.jython.egg-info/PKG-INFO
src/jtypes.jython.egg-info/SOURCES.txt
src/jtypes.jython.egg-info/dependency_links.txt
src/jtypes.jython.egg-info/namespace_packages.txt
src/jtypes.jython.egg-info/requires.txt
src/jtypes.jython.egg-info/top_level.txt
src/jtypes.jython.egg-info/zip-safe
tests/__init__.py
tests/__main__.py
tests/run.py
tests/java/classes/javatests/AnonInner$1.class
tests/java/classes/javatests/AnonInner.class
tests/java/classes/javatests/BigDecimalTest.class
tests/java/classes/javatests/Dict2JavaTest.class
tests/java/classes/javatests/ExtendedInterface.class
tests/java/classes/javatests/Foo.class
tests/java/classes/javatests/Inheritance.class
tests/java/classes/javatests/InheritanceA.class
tests/java/classes/javatests/InheritanceB.class
tests/java/classes/javatests/InheritanceC.class
tests/java/classes/javatests/InheritanceD.class
tests/java/classes/javatests/JOverload.class
tests/java/classes/javatests/ProxyTests$NullToString.class
tests/java/classes/javatests/ProxyTests$Person.class
tests/java/classes/javatests/ProxyTests.class
tests/java/classes/javatests/StackOverflowErrorTest.class
tests/java/classes/javatests/SubFoo.class
tests/java/classes/javatests/UseExtendedInterface.class
tests/java/javatests/AnonInner.java
tests/java/javatests/BigDecimalTest.java
tests/java/javatests/Dict2JavaTest.java
tests/java/javatests/ExtendedInterface.java
tests/java/javatests/Foo.java
tests/java/javatests/Inheritance.java
tests/java/javatests/InheritanceA.java
tests/java/javatests/InheritanceB.java
tests/java/javatests/InheritanceC.java
tests/java/javatests/InheritanceD.java
tests/java/javatests/JOverload.java
tests/java/javatests/ProxyTests.java
tests/java/javatests/StackOverflowErrorTest.java
tests/java/javatests/SubFoo.java
tests/java/javatests/UseExtendedInterface.java
tests/python/__init__.py